LICENSE.txt
MANIFEST.in
README.rst
setup.py
django_quick_test.egg-info/PKG-INFO
django_quick_test.egg-info/SOURCES.txt
django_quick_test.egg-info/dependency_links.txt
django_quick_test.egg-info/not-zip-safe
django_quick_test.egg-info/requires.txt
django_quick_test.egg-info/top_level.txt
quick_test/__init__.py
quick_test/plugin.py
quick_test/testrunner.py
quick_test/management/__init__.py
quick_test/management/commands/__init__.py
quick_test/management/commands/quick_test.py