Metadata-Version: 1.0
Name: django-quick-test
Version: 0.3.0
Summary: Django test runner that separates test database creation and test running
Home-page: https://github.com/martinrusev/django-quick-test
Author: Martin Rusev
Author-email: martinrusev@live.com
License: BSD
Keywords: django,tests,nose,
Platform: UNKNOWN
Classifier: Programming Language :: Python
Classifier: Topic :: Software Development :: Libraries :: Python Modules
Classifier: Framework :: Django
Classifier: Environment :: Web Environment
